MANIFEST.in
README.txt
setup.py
docs/HISTORY.txt
docs/README.txt
src/ztfy/__init__.py
src/ztfy.hplskin.egg-info/PKG-INFO
src/ztfy.hplskin.egg-info/SOURCES.txt
src/ztfy.hplskin.egg-info/dependency_links.txt
src/ztfy.hplskin.egg-info/entry_points.txt
src/ztfy.hplskin.egg-info/namespace_packages.txt
src/ztfy.hplskin.egg-info/not-zip-safe
src/ztfy.hplskin.egg-info/requires.txt
src/ztfy.hplskin.egg-info/top_level.txt
src/ztfy/hplskin/__init__.py
src/ztfy/hplskin/banner.py
src/ztfy/hplskin/blog.py
src/ztfy/hplskin/configure.zcml
src/ztfy/hplskin/html.py
src/ztfy/hplskin/interfaces.py
src/ztfy/hplskin/layer.py
src/ztfy/hplskin/menu.py
src/ztfy/hplskin/section.py
src/ztfy/hplskin/site.py
src/ztfy/hplskin/topic.py
src/ztfy/hplskin/doctests/README.txt
src/ztfy/hplskin/locales/ztfy.hplskin.pot
src/ztfy/hplskin/locales/en/LC_MESSAGES/ztfy.hplskin.mo
src/ztfy/hplskin/locales/en/LC_MESSAGES/ztfy.hplskin.po
src/ztfy/hplskin/locales/fr/LC_MESSAGES/ztfy.hplskin.mo
src/ztfy/hplskin/locales/fr/LC_MESSAGES/ztfy.hplskin.po
src/ztfy/hplskin/resources/css/hpl.css
src/ztfy/hplskin/resources/css/hpl.min.css
src/ztfy/hplskin/resources/img/dot-off.png
src/ztfy/hplskin/resources/img/dot.png
src/ztfy/hplskin/resources/js/hpl.js
src/ztfy/hplskin/resources/js/hpl.min.js
src/ztfy/hplskin/templates/layout.pt
src/ztfy/hplskin/templates/section_sections.pt
src/ztfy/hplskin/templates/topic_list.pt
src/ztfy/hplskin/tests/__init__.py
src/ztfy/hplskin/tests/test_hplskindocs.py
src/ztfy/hplskin/tests/test_hplskindocstrings.py
src/ztfy/hplskin/viewlets/__init__.py
src/ztfy/hplskin/viewlets/header/__init__.py
src/ztfy/hplskin/viewlets/header/banner.pt
src/ztfy/hplskin/viewlets/header/banner.py
src/ztfy/hplskin/viewlets/header/configure.zcml
src/ztfy/hplskin/viewlets/sections/__init__.py
src/ztfy/hplskin/viewlets/sections/configure.zcml
src/ztfy/hplskin/viewlets/sections/sections.pt